file_tree_fsl/load.py
file_tree_fsl/test_load.py
file_tree_fsl/trees/HCP_directory.tree
file_tree_fsl/trees/HCP_surface.tree
file_tree_fsl/trees/bedpostx.tree
file_tree_fsl/trees/bet.tree
file_tree_fsl/trees/bids_raw.tree
file_tree_fsl/trees/diffusion.tree
file_tree_fsl/trees/dti.tree
file_tree_fsl/trees/eddy.tree
file_tree_fsl/trees/epi_reg.tree
file_tree_fsl/trees/fast.tree
file_tree_fsl/trees/feat.tree
file_tree_fsl/trees/feat_reg.tree
file_tree_fsl/trees/feat_stats.tree
file_tree_fsl/trees/freesurfer.tree
file_tree_fsl/trees/fsl_anat.tree
file_tree_fsl/trees/gfeat.tree
file_tree_fsl/trees/probtrackx.tree
file_tree_fsl/trees/tbss.tree
file_tree_fsl/trees/topup.tree
file_tree_fsl/trees/vbm.tree
file_tree_fsl/trees/xtract.tree
file_tree_fsl-0.2.3.dist-info/LICENSE
file_tree_fsl-0.2.3.dist-info/METADATA
file_tree_fsl-0.2.3.dist-info/WHEEL
file_tree_fsl-0.2.3.dist-info/entry_points.txt
file_tree_fsl-0.2.3.dist-info/top_level.txt
file_tree_fsl-0.2.3.dist-info/RECORD
